nlpg/__init__.py
nlpg/__main__.py
nlpg/nlpg.db
nlpg/nlpg.py
nlpg/nlpg.sql
nlpg-1.0.0.dist-info/METADATA
nlpg-1.0.0.dist-info/WHEEL
nlpg-1.0.0.dist-info/entry_points.txt
nlpg-1.0.0.dist-info/licenses/LICENSE
nlpg-1.0.0.dist-info/RECORD
