Metadata-Version: 2.4
Name: nlpg
Version: 1.0.0
Summary: Ready to use Natural Language Password Generator.
License-Expression: GPL-3.0
License-File: LICENSE
Requires-Python: >=3.7
